setup.py
nnClassifier.egg-info/PKG-INFO
nnClassifier.egg-info/SOURCES.txt
nnClassifier.egg-info/dependency_links.txt
nnClassifier.egg-info/top_level.txt
src/Constants.py
src/Evaluator_.py
src/ImageCropper_.py
src/Main_.py
src/MyUtils_.py
src/NeuralNetwork_.py
src/Pickler_.py
src/Predictor_.py
src/Transfer_Calculator_.py
src/__init__.py
src/cache.py
src/dataset.py
src/download.py
src/inception.py
src/inception5h.py